pytonik_curl/Version.py
pytonik_curl/__init__.py
pytonik_curl/curl.py
pytonik_curl-2.0.dist-info/LICENSE.txt
pytonik_curl-2.0.dist-info/METADATA
pytonik_curl-2.0.dist-info/WHEEL
pytonik_curl-2.0.dist-info/top_level.txt
pytonik_curl-2.0.dist-info/RECORD
