Metadata-Version: 2.1
Name: pytonik-curl
Version: 2.0
Summary: pytonik curl is built to transfer data using various network protocols and support sending or initiating actions within or outside protocols.
Home-page: https://pytonik-curl.readthedocs.io
Author: pytonik
Author-email: info@pytonik.com
Maintainer: Emmanuel Essien
Maintainer-email: emmamartinscm@gmail.com
License: MIT
Keywords: oop,module,python,framework,web,app,curl,api,protocols,network
Platform: UNKNOWN
Classifier: Environment :: Console
Classifier: License :: OSI Approved :: MIT License
Classifier: Environment :: Web Environment
Classifier: Intended Audience :: End Users/Desktop
Classifier: Intended Audience :: Developers
Classifier: Intended Audience :: System Administrators
Classifier: License :: OSI Approved :: Python Software Foundation License
Classifier: Programming Language :: Python
Classifier: Topic :: Office/Business
Classifier: Intended Audience :: Developers
Classifier: License :: OSI Approved :: MIT License
Classifier: Operating System :: OS Independent
Classifier: Programming Language :: Python :: 2.7
Classifier: Programming Language :: Python :: 3
Classifier: Programming Language :: Python :: 3.4
Classifier: Programming Language :: Python :: 3.5
Classifier: Programming Language :: Python :: 3.6
Classifier: Programming Language :: Python :: 3.7
Classifier: Programming Language :: Python :: 3.8
Classifier: Programming Language :: Python :: 3.9
Classifier: Programming Language :: Python
Requires-Python: >=2.7, >=2.7.*, >=3.*
